aiobittrexapi/__init__.py
aiobittrexapi/const.py
aiobittrexapi/errors.py
aiobittrexapi/utils.py
aiobittrexapi-1.4.0.dist-info/LICENSE
aiobittrexapi-1.4.0.dist-info/METADATA
aiobittrexapi-1.4.0.dist-info/WHEEL
aiobittrexapi-1.4.0.dist-info/top_level.txt
aiobittrexapi-1.4.0.dist-info/RECORD
