Metadata-Version: 2.1
Name: aiobittrexapi
Version: 1.4.0
Summary: Asynchronous Python wrapper for the Bittrex API.
Home-page: https://github.com/DevSecNinja/aiobittrexapi
Author: Jean-Paul van Ravensberg
Author-email: 14926452+DevSecNinja@users.noreply.github.com
License: MIT license
Keywords: bittrex,bittrex-api,bittrex-v3,cryptocurrency,api,async,client
Platform: UNKNOWN
Classifier: Framework :: AsyncIO
Classifier: Intended Audience :: Developers
Classifier: License :: OSI Approved :: MIT License
Classifier: Natural Language :: English
Classifier: Programming Language :: Python :: 3.7
Classifier: Programming Language :: Python :: 3.8
Classifier: Programming Language :: Python :: 3
Classifier: Topic :: Software Development :: Libraries :: Python Modules
Requires-Dist: aiohttp (>=3.0.0)
Requires-Dist: asyncio-throttle (>=0.1.1)
